README.md
setup.cfg
setup.py
urban_transit_network_analysis/AnalysManager.py
urban_transit_network_analysis/__init__.py
urban_transit_network_analysis.egg-info/PKG-INFO
urban_transit_network_analysis.egg-info/SOURCES.txt
urban_transit_network_analysis.egg-info/dependency_links.txt
urban_transit_network_analysis.egg-info/requires.txt
urban_transit_network_analysis.egg-info/top_level.txt
urban_transit_network_analysis/context/AnalysContext.py
urban_transit_network_analysis/context/DBGraphParameters.py
urban_transit_network_analysis/context/GraphAnalysContext.py
urban_transit_network_analysis/context/MetricCalculationContext.py
urban_transit_network_analysis/context/PrintGraphAnalysContext.py
urban_transit_network_analysis/context/__init__.py
urban_transit_network_analysis/data/calculator/MetricDataCalculator.py
urban_transit_network_analysis/data/calculator/__init__.py
urban_transit_network_analysis/data/preparer/MetricDataPreparer.py
urban_transit_network_analysis/data/preparer/__init__.py
urban_transit_network_analysis/database/AnalysPreparer.py
urban_transit_network_analysis/database/CommunityDetection.py
urban_transit_network_analysis/database/GraphDbManager.py
urban_transit_network_analysis/database/MetricsCalculate.py
urban_transit_network_analysis/database/MetricsDistribution.py
urban_transit_network_analysis/database/Neo4jConnection.py
urban_transit_network_analysis/database/__init__.py
urban_transit_network_analysis/enums/ClusteringTypes.py
urban_transit_network_analysis/enums/GraphTypes.py
urban_transit_network_analysis/enums/HeatMapMetrics.py
urban_transit_network_analysis/enums/HistogramMetrics.py
urban_transit_network_analysis/enums/__init__.py
urban_transit_network_analysis/graphics/Printer.py
urban_transit_network_analysis/graphics/__init__.py
urban_transit_network_analysis/parser/Parser.py
urban_transit_network_analysis/parser/__init__.py
urban_transit_network_analysis/utils/GraphUtils.py
urban_transit_network_analysis/utils/__init__.py