Metadata-Version: 2.1
Name: urban-transit-network-analysis
Version: 1.0.5
Summary: Python module for urban network analysis
Home-page: https://github.com/DanilPomortsev/Urban-Transit-Network-Analysis
Author: DPomortsev
Author-email: danul78969@gmail.com
